svg_model/__init__.py
svg_model/body_group.py
svg_model/circles.svg
svg_model/color.py
svg_model/connections.py
svg_model/data_frame.py
svg_model/detect_connections.py
svg_model/draw.py
svg_model/geo_path.py
svg_model/gui_demo.py
svg_model/loop.py
svg_model/merge.py
svg_model/path_group.py
svg_model/plot.py
svg_model/point_query.py
svg_model/seidel.py
svg_model/shapes_canvas.py
svg_model/tesselate.py
svg_model/bin/__init__.py
svg_model/bin/detect_connections.py
svg_model/svgload/__init__.py
svg_model/svgload/path_parser.py
svg_model/svgload/svg_parser.py
svg_model-0.6.post2.dist-info/DESCRIPTION.rst
svg_model-0.6.post2.dist-info/METADATA
svg_model-0.6.post2.dist-info/RECORD
svg_model-0.6.post2.dist-info/WHEEL
svg_model-0.6.post2.dist-info/metadata.json
svg_model-0.6.post2.dist-info/pbr.json
svg_model-0.6.post2.dist-info/top_level.txt
