Metadata-Version: 2.0
Name: svg-model
Version: 0.6.post2
Summary: A Python module for parsing an SVG file to a group of paths.
Home-page: http://github.com/wheeler-microfluidics/svg_model.git
Author: Christian Fobel
Author-email: christian@fobel.net
License: LGPLv2.1
Keywords: svg model pymunk
Platform: UNKNOWN
Requires-Dist: lxml
Requires-Dist: pandas (>=0.17.0)
Requires-Dist: path-helpers
Requires-Dist: pint
Requires-Dist: pymunk (>=4.0.0,<5.0)
Requires-Dist: svgwrite
